ntc_rosetta/__init__.py
ntc_rosetta/cli/__init__.py
ntc_rosetta/cli/linter.py
ntc_rosetta/cli/print_model.py
ntc_rosetta/cli/print_processor.py
ntc_rosetta/drivers/__init__.py
ntc_rosetta/drivers/base.py
ntc_rosetta/drivers/ios.py
ntc_rosetta/drivers/junos.py
ntc_rosetta/helpers/__init__.py
ntc_rosetta/helpers/ios.py
ntc_rosetta/helpers/json_helpers.py
ntc_rosetta/helpers/xml_helpers.py
ntc_rosetta/parsers/__init__.py
ntc_rosetta/parsers/ntc/__init__.py
ntc_rosetta/parsers/ntc/ios/__init__.py
ntc_rosetta/parsers/ntc/ios/ntc_vlan/__init__.py
ntc_rosetta/parsers/ntc/ios/ntc_vlan/vlan.py
ntc_rosetta/parsers/ntc/junos/__init__.py
ntc_rosetta/parsers/openconfig/ios/__init__.py
ntc_rosetta/parsers/openconfig/ios/openconfig_if_ethernet/__init__.py
ntc_rosetta/parsers/openconfig/ios/openconfig_if_ethernet/ethernet.py
ntc_rosetta/parsers/openconfig/ios/openconfig_interfaces/__init__.py
ntc_rosetta/parsers/openconfig/ios/openconfig_interfaces/interfaces.py
ntc_rosetta/parsers/openconfig/ios/openconfig_network_instance/__init__.py
ntc_rosetta/parsers/openconfig/ios/openconfig_network_instance/network_instances.py
ntc_rosetta/parsers/openconfig/ios/openconfig_system/__init__.py
ntc_rosetta/parsers/openconfig/ios/openconfig_system/system.py
ntc_rosetta/parsers/openconfig/ios/openconfig_vlan/__init__.py
ntc_rosetta/parsers/openconfig/ios/openconfig_vlan/switched_vlan.py
ntc_rosetta/parsers/openconfig/ios/openconfig_vlan/vlans.py
ntc_rosetta/parsers/openconfig/junos/__init__.py
ntc_rosetta/parsers/openconfig/junos/helpers.py
ntc_rosetta/parsers/openconfig/junos/openconfig_if_ethernet/__init__.py
ntc_rosetta/parsers/openconfig/junos/openconfig_if_ethernet/ethernet.py
ntc_rosetta/parsers/openconfig/junos/openconfig_interfaces/__init__.py
ntc_rosetta/parsers/openconfig/junos/openconfig_interfaces/interfaces.py
ntc_rosetta/parsers/openconfig/junos/openconfig_network_instance/__init__.py
ntc_rosetta/parsers/openconfig/junos/openconfig_network_instance/network_instances.py
ntc_rosetta-0.2.1.dist-info/entry_points.txt
ntc_rosetta-0.2.1.dist-info/LICENSE
ntc_rosetta-0.2.1.dist-info/WHEEL
ntc_rosetta-0.2.1.dist-info/METADATA
ntc_rosetta-0.2.1.dist-info/RECORD
